pypinyin_g2pw/__init__.py
pypinyin_g2pw/g2pw.py
pypinyin_g2pw-0.4.0.dist-info/LICENSE
pypinyin_g2pw-0.4.0.dist-info/METADATA
pypinyin_g2pw-0.4.0.dist-info/WHEEL
pypinyin_g2pw-0.4.0.dist-info/top_level.txt
pypinyin_g2pw-0.4.0.dist-info/RECORD
