Metadata-Version: 2.1
Name: pypinyin-g2pw
Version: 0.4.0
Summary: 基于 g2pW 提升 pypinyin 的准确性。
Home-page: https://github.com/mozillazg/pypinyin-g2pW
Author: mozillazg
Author-email: mozillazg101@gmail.com
License: UNKNOWN
Project-URL: Bug Tracker, https://github.com/mozillazg/pypinyin-g2pW/issues
Platform: UNKNOWN
Classifier: Programming Language :: Python :: 3
Classifier: License :: OSI Approved :: MIT License
Classifier: Operating System :: OS Independent
Requires-Python: >=3.6, <4
Requires-Dist: g2pw (>=0.1.1)
Requires-Dist: pypinyin (>=0.47.1)
